{
    "data" : 
[
    
    {
    "name": "Blog",
    "permalink" : "https://toddpipe.netlify.app/posts/"
}

    
    , {
    "name": "Manufacturers",
    "permalink" : "https://toddpipe.netlify.app/manufacturers/"
}

    
    , {
    "name": "Resources",
    "permalink" : "https://toddpipe.netlify.app/resources/"
}

    
    , {
    "name": "Company",
    "permalink" : "https://toddpipe.netlify.app/company/"
}

    
    , {
    "title": "Locations",
    "permalink": "https://toddpipe.netlify.app/locations/",
    "subtitle": "Serving Southern California",
    "address": "<no value>",
    "city": "<no value>",
    "state": "<no value>",
    "zipcode": "<no value>",
    "phone": "<no value>",
    "fax": "<no value>"
}

    
]

}
